LICENSE
pyraptor/__init__.py
pyraptor/dao/__init__.py
pyraptor/dao/timetable.py
pyraptor/gtfs/__init__.py
pyraptor/gtfs/timetable.py
pyraptor/model/__init__.py
pyraptor/model/mcraptor.py
pyraptor/model/raptor.py
pyraptor/model/structures.py
pyraptor/query_mcraptor.py
pyraptor/query_range_mcraptor.py
pyraptor/query_range_raptor.py
pyraptor/query_raptor.py
pyraptor/util.py
pyraptor-1.3.9.dist-info/LICENSE
pyraptor-1.3.9.dist-info/WHEEL
pyraptor-1.3.9.dist-info/METADATA
pyraptor-1.3.9.dist-info/RECORD
