Metadata-Version: 2.1
Name: pyraptor
Version: 1.3.9
Summary: Journey planner with RAPTOR algorithm
Home-page: https://github.com/lmeulen/pyraptor
License: MIT
Author: Leo van der Meulen, Thom Hopmans
Requires-Python: >=3.8,<4.0
Classifier: License :: OSI Approved :: MIT License
Classifier: Programming Language :: Python :: 3
Classifier: Programming Language :: Python :: 3.10
Classifier: Programming Language :: Python :: 3.8
Classifier: Programming Language :: Python :: 3.9
Requires-Dist: joblib (>=1.0.1,<2.0.0)
Requires-Dist: loguru (>=0.6.0,<0.7.0)
Requires-Dist: pandas (>=1.4.0,<2.0.0)
Project-URL: Repository, https://github.com/lmeulen/pyraptor
